bib2table/__init__.py
bib2table/__main__.py
bib2table-0.1.0.dist-info/LICENSE
bib2table-0.1.0.dist-info/METADATA
bib2table-0.1.0.dist-info/WHEEL
bib2table-0.1.0.dist-info/entry_points.txt
bib2table-0.1.0.dist-info/RECORD
