Metadata-Version: 2.3
Name: bib2table
Version: 0.1.0
Summary: Convert a .bib file to a table in a variety of output formats
License: MIT License
Author: Andrei Olar
Author-email: andrei.olar@gmail.com
Requires-Python: >=3.13
Classifier: License :: Other/Proprietary License
Classifier: Programming Language :: Python :: 3
Classifier: Programming Language :: Python :: 3.13
Requires-Dist: bibtexparser (>=1.4.3,<2.0.0)
Requires-Dist: click (>=8.2.1,<9.0.0)
